prefect_ray/__init__.py
prefect_ray/_version.py
prefect_ray/context.py
prefect_ray/task_runners.py
prefect_ray-0.4.5.dist-info/licenses/LICENSE
prefect_ray-0.4.5.dist-info/METADATA
prefect_ray-0.4.5.dist-info/WHEEL
prefect_ray-0.4.5.dist-info/entry_points.txt
prefect_ray-0.4.5.dist-info/top_level.txt
prefect_ray-0.4.5.dist-info/RECORD
