Metadata-Version: 2.4
Name: prefect-ray
Version: 0.4.5
Summary: Prefect integrations with the Ray execution framework.
Author-email: "Prefect Technologies, Inc." <help@prefect.io>
License: Apache License 2.0
Project-URL: Homepage, https://github.com/PrefectHQ/prefect/tree/main/src/integrations/prefect-ray
Keywords: prefect
Classifier: Natural Language :: English
Classifier: Intended Audience :: Developers
Classifier: Intended Audience :: System Administrators
Classifier: License :: OSI Approved :: Apache Software License
Classifier: Programming Language :: Python :: 3 :: Only
Classifier: Programming Language :: Python :: 3.9
Classifier: Programming Language :: Python :: 3.10
Classifier: Programming Language :: Python :: 3.11
Classifier: Programming Language :: Python :: 3.12
Classifier: Topic :: Software Development :: Libraries
Requires-Python: !=3.13,>=3.9
License-File: LICENSE
Requires-Dist: prefect>=3.4.7
Requires-Dist: ray[default]>=2.0.0
Dynamic: license-file
